PyNIT-0.1.16.data/scripts/antsSyN
PyNIT-0.1.16.data/scripts/brk2nifti
PyNIT-0.1.16.data/scripts/check_reg
PyNIT-0.1.16.data/scripts/checkbrk
PyNIT-0.1.16.data/scripts/checkscans
PyNIT-0.1.16.data/scripts/onesample_ttest
PyNIT-0.1.16.data/scripts/pynit
PyNIT-0.1.16.dist-info/DESCRIPTION.rst
PyNIT-0.1.16.dist-info/METADATA
PyNIT-0.1.16.dist-info/RECORD
PyNIT-0.1.16.dist-info/WHEEL
PyNIT-0.1.16.dist-info/metadata.json
PyNIT-0.1.16.dist-info/top_level.txt
pynit/__init__.py
pynit/analysis/__init__.py
pynit/analysis/dynamic.py
pynit/analysis/network.py
pynit/analysis/timeseries.py
pynit/bin/__init__.py
pynit/handler/__init__.py
pynit/handler/base.py
pynit/handler/images.py
pynit/handler/project.py
pynit/handler/step.py
pynit/handler/tests/__init__.py
pynit/handler/tests/test_base.py
pynit/pipelines/__init__.py
pynit/pipelines/base.py
pynit/pipelines/pipelines.py
pynit/process/__init__.py
pynit/process/afni.py
pynit/process/ants.py
pynit/process/base.py
pynit/process/fsl.py
pynit/process/nsp.py
pynit/tools/__init__.py
pynit/tools/gui.py
pynit/tools/messages.py
pynit/tools/methods.py
pynit/tools/visualizers.py
