Metadata-Version: 2.0
Name: PyNIT
Version: 0.1.16
Summary: Python NeuroImaging Toolkit
Home-page: https://dvm-shlee.github.io
Author: SungHo Lee
Author-email: shlee@unc.edu
License: GNLv3
Keywords: Python NeuroImaging Toolkit
Platform: UNKNOWN
Classifier: Development Status :: 4 - Beta
Classifier: Framework :: Jupyter
Classifier: Intended Audience :: Science/Research
Classifier: Topic :: Scientific/Engineering :: Information Analysis
Classifier: Natural Language :: English
Classifier: Programming Language :: Python :: 2.7
Requires-Dist: jupyter (>=1.0.0)
Requires-Dist: tqdm
Requires-Dist: pandas
Requires-Dist: openpyxl
Requires-Dist: xlrd
Requires-Dist: nibabel
Requires-Dist: matplotlib
Requires-Dist: seaborn
Requires-Dist: scikit-image
Requires-Dist: numpy
Requires-Dist: scipy
Requires-Dist: scikit-learn
Requires-Dist: psutil
Requires-Dist: pynsp
